[
    {
        "x1": 53,
        "y1": 306,
        "x2": 113,
        "y2": 318,
        "txt": "판토시딜캡슐"
    },
    {
        "x1": 53,
        "y1": 323,
        "x2": 189,
        "y2": 336,
        "txt": "트리가정(트리메부틴말레산염)"
    },
    {
        "x1": 53,
        "y1": 341,
        "x2": 217,
        "y2": 354,
        "txt": "제이케이(JK)정10밀리그램(타다라필)"
    },
    {
        "x1": 53,
        "y1": 360,
        "x2": 219,
        "y2": 373,
        "txt": "훼로웰주(수크로스수산화제이철착염)"
    },
    {
        "x1": 53,
        "y1": 378,
        "x2": 129,
        "y2": 391,
        "txt": "게리동정(수출용)"
    },
    {
        "x1": 53,
        "y1": 397,
        "x2": 237,
        "y2": 410,
        "txt": "아시브로캡슐100밀리그램(아세브로필린)"
    },
    {
        "x1": 53,
        "y1": 414,
        "x2": 225,
        "y2": 427,
        "txt": "엑시글루정5밀리그램(다파글리플로진)"
    },
    {
        "x1": 53,
        "y1": 433,
        "x2": 149,
        "y2": 446,
        "txt": "화일결정트립신(원료)"
    },
    {
        "x1": 53,
        "y1": 449,
        "x2": 230,
        "y2": 462,
        "txt": "아신돌캡슐200밀리그램(에토돌락)(수출"
    },
    {
        "x1": 280,
        "y1": 306,
        "x2": 286,
        "y2": 317,
        "txt": "4"
    },
    {
        "x1": 280,
        "y1": 323,
        "x2": 286,
        "y2": 334,
        "txt": "9"
    },
    {
        "x1": 280,
        "y1": 341,
        "x2": 286,
        "y2": 352,
        "txt": "7"
    },
    {
        "x1": 280,
        "y1": 360,
        "x2": 286,
        "y2": 371,
        "txt": "1"
    },
    {
        "x1": 280,
        "y1": 378,
        "x2": 286,
        "y2": 389,
        "txt": "6"
    },
    {
        "x1": 280,
        "y1": 397,
        "x2": 286,
        "y2": 408,
        "txt": "7"
    },
    {
        "x1": 280,
        "y1": 414,
        "x2": 286,
        "y2": 425,
        "txt": "6"
    },
    {
        "x1": 280,
        "y1": 433,
        "x2": 286,
        "y2": 444,
        "txt": "2"
    },
    {
        "x1": 280,
        "y1": 449,
        "x2": 292,
        "y2": 460,
        "txt": "10"
    },
    {
        "x1": 314,
        "y1": 306,
        "x2": 320,
        "y2": 317,
        "txt": "5"
    },
    {
        "x1": 314,
        "y1": 323,
        "x2": 320,
        "y2": 334,
        "txt": "9"
    },
    {
        "x1": 314,
        "y1": 341,
        "x2": 320,
        "y2": 352,
        "txt": "5"
    },
    {
        "x1": 314,
        "y1": 360,
        "x2": 320,
        "y2": 371,
        "txt": "4"
    },
    {
        "x1": 314,
        "y1": 378,
        "x2": 320,
        "y2": 389,
        "txt": "9"
    },
    {
        "x1": 314,
        "y1": 397,
        "x2": 320,
        "y2": 408,
        "txt": "5"
    },
    {
        "x1": 314,
        "y1": 414,
        "x2": 320,
        "y2": 425,
        "txt": "3"
    },
    {
        "x1": 314,
        "y1": 433,
        "x2": 320,
        "y2": 444,
        "txt": "5"
    },
    {
        "x1": 314,
        "y1": 449,
        "x2": 320,
        "y2": 460,
        "txt": "9"
    },
    {
        "x1": 353,
        "y1": 306,
        "x2": 359,
        "y2": 317,
        "txt": "4"
    },
    {
        "x1": 353,
        "y1": 323,
        "x2": 359,
        "y2": 334,
        "txt": "3"
    },
    {
        "x1": 353,
        "y1": 341,
        "x2": 359,
        "y2": 352,
        "txt": "1"
    },
    {
        "x1": 353,
        "y1": 360,
        "x2": 359,
        "y2": 371,
        "txt": "1"
    },
    {
        "x1": 353,
        "y1": 378,
        "x2": 359,
        "y2": 389,
        "txt": "5"
    },
    {
        "x1": 353,
        "y1": 397,
        "x2": 359,
        "y2": 408,
        "txt": "6"
    },
    {
        "x1": 353,
        "y1": 414,
        "x2": 359,
        "y2": 425,
        "txt": "1"
    },
    {
        "x1": 353,
        "y1": 433,
        "x2": 359,
        "y2": 444,
        "txt": "1"
    },
    {
        "x1": 353,
        "y1": 449,
        "x2": 365,
        "y2": 460,
        "txt": "12"
    },
    {
        "x1": 53,
        "y1": 557,
        "x2": 133,
        "y2": 569,
        "txt": "헤파센스연질캡슐"
    },
    {
        "x1": 53,
        "y1": 574,
        "x2": 140,
        "y2": 587,
        "txt": "듀얼살탄정40/5mg"
    },
    {
        "x1": 53,
        "y1": 592,
        "x2": 257,
        "y2": 605,
        "txt": "글리플로정5mg(다파글리플로진무수유당혼합"
    },
    {
        "x1": 53,
        "y1": 612,
        "x2": 113,
        "y2": 624,
        "txt": "프레스탑연고"
    },
    {
        "x1": 53,
        "y1": 629,
        "x2": 246,
        "y2": 642,
        "txt": "간타모스정(비페닐디메틸디카르복실레이트"
    },
    {
        "x1": 282,
        "y1": 557,
        "x2": 288,
        "y2": 568,
        "txt": "7"
    },
    {
        "x1": 282,
        "y1": 574,
        "x2": 288,
        "y2": 585,
        "txt": "9"
    },
    {
        "x1": 282,
        "y1": 592,
        "x2": 288,
        "y2": 603,
        "txt": "8"
    },
    {
        "x1": 282,
        "y1": 612,
        "x2": 288,
        "y2": 623,
        "txt": "1"
    },
    {
        "x1": 282,
        "y1": 629,
        "x2": 288,
        "y2": 640,
        "txt": "1"
    },
    {
        "x1": 316,
        "y1": 557,
        "x2": 322,
        "y2": 568,
        "txt": "2"
    },
    {
        "x1": 316,
        "y1": 574,
        "x2": 322,
        "y2": 585,
        "txt": "8"
    },
    {
        "x1": 316,
        "y1": 592,
        "x2": 322,
        "y2": 603,
        "txt": "1"
    },
    {
        "x1": 316,
        "y1": 612,
        "x2": 322,
        "y2": 623,
        "txt": "4"
    },
    {
        "x1": 316,
        "y1": 629,
        "x2": 322,
        "y2": 640,
        "txt": "9"
    },
    {
        "x1": 354,
        "y1": 557,
        "x2": 366,
        "y2": 568,
        "txt": "14"
    },
    {
        "x1": 354,
        "y1": 574,
        "x2": 360,
        "y2": 585,
        "txt": "5"
    },
    {
        "x1": 354,
        "y1": 592,
        "x2": 360,
        "y2": 603,
        "txt": "6"
    },
    {
        "x1": 354,
        "y1": 612,
        "x2": 360,
        "y2": 623,
        "txt": "7"
    },
    {
        "x1": 354,
        "y1": 629,
        "x2": 360,
        "y2": 640,
        "txt": "7"
    },
    {
        "x1": 391,
        "y1": 306,
        "x2": 481,
        "y2": 318,
        "txt": "경보세프테졸나트륨"
    },
    {
        "x1": 392,
        "y1": 541,
        "x2": 484,
        "y2": 553,
        "txt": "파비라졸정10밀리그"
    },
    {
        "x1": 292,
        "y1": 134,
        "x2": 302,
        "y2": 146,
        "txt": "■"
    },
    {
        "x1": 332,
        "y1": 135,
        "x2": 339,
        "y2": 146,
        "txt": "A"
    },
    {
        "x1": 312,
        "y1": 540,
        "x2": 322,
        "y2": 552,
        "txt": "■"
    }
]